Metadata-Version: 2.1
Name: densify
Version: 1.0.0
Summary: Algorithm for oversampling point clouds
Home-page: https://github.com/shobrook/densify
Author: shobrook
Author-email: shobrookj@gmail.com
License: MIT
Keywords: oversampling,point-cloud,machine-learning,regularization
Platform: UNKNOWN
Requires-Python: >=3
License-File: LICENSE
